{"_id":"hubot-sendgrid","_rev":"3-704aa44d91433b42dbc5967e1d04e919","name":"hubot-sendgrid","description":"SendGrid plugin for hubot","dist-tags":{"latest":"0.2.0"},"versions":{"0.1.1":{"name":"hubot-sendgrid","description":"SendGrid plugin for hubot","version":"0.1.1","author":{"name":"Jason Staten","email":"jstaten07@gmail.com"},"license":"MIT","keywords":["hubot","hubot-scripts"],"repository":{"type":"git","url":"https://github.com/statianzo/hubot-sendgrid.git"},"bugs":{"url":"https://github.com/statianzo/hubot-sendgrid/issues"},"dependencies":{"coffee-script":"^1.8.0"},"main":"index.coffee","scripts":{"test":"nodeunit --reporter skip_passed"},"devDependencies":{"nodeunit":"^0.9.0"},"gitHead":"17905c59032deb4b2ee5e3625d00c824def5270a","homepage":"https://github.com/statianzo/hubot-sendgrid","_id":"hubot-sendgrid@0.1.1","_shasum":"4bed8b56dbed1fbf2d6d3d86115d302b515b3978","_from":".","_npmVersion":"2.1.5","_nodeVersion":"0.10.32","_npmUser":{"name":"statianzo","email":"jstaten07+npm@gmail.com"},"maintainers":[{"name":"statianzo","email":"jstaten07+npm@gmail.com"}],"dist":{"shasum":"4bed8b56dbed1fbf2d6d3d86115d302b515b3978","tarball":"http://registry.npmjs.org/hubot-sendgrid/-/hubot-sendgrid-0.1.1.tgz"}},"0.2.0":{"name":"hubot-sendgrid","description":"SendGrid plugin for hubot","version":"0.2.0","author":{"name":"Jason Staten","email":"jstaten07@gmail.com"},"license":"MIT","keywords":["hubot","hubot-scripts"],"repository":{"type":"git","url":"https://github.com/statianzo/hubot-sendgrid.git"},"bugs":{"url":"https://github.com/statianzo/hubot-sendgrid/issues"},"dependencies":{"coffee-script":"^1.8.0"},"main":"index.coffee","scripts":{"test":"nodeunit --reporter skip_passed"},"devDependencies":{"nodeunit":"^0.9.0"},"gitHead":"7f87bb68cb31e1045136db609ac6fc4bbee3af22","homepage":"https://github.com/statianzo/hubot-sendgrid","_id":"hubot-sendgrid@0.2.0","_shasum":"151a88b10c1bd73cf905ebba18b6a66aa6eff6df","_from":".","_npmVersion":"2.1.5","_nodeVersion":"0.10.33","_npmUser":{"name":"statianzo","email":"jstaten07+npm@gmail.com"},"maintainers":[{"name":"statianzo","email":"jstaten07+npm@gmail.com"}],"dist":{"shasum":"151a88b10c1bd73cf905ebba18b6a66aa6eff6df","tarball":"http://registry.npmjs.org/hubot-sendgrid/-/hubot-sendgrid-0.2.0.tgz"}}},"readme":"# hubot-sendgrid\n\nSendGrid commands for hubot\n\n## Installation\n\n```\nnpm install --save hubot-sendgrid\n```\n\nAdd `\"hubot-sendgrid\"` into your hubot project's `external-scripts.json`\n\nSet `HUBOT_SENDGRID_USER` to your SendGrid user\n\nSet `HUBOT_SENDGRID_KEY` to your SendGrid API key (password)\n\n## Usage\n\n\n#### Statistics\n\n```\nhubot sendgrid stats\n\nhubot sendgrid stats YYYY-MM-DD\n```\n\n#### Blocks, Bounces, Invalids, Unsubscribes, and Spam Reports\n\n```\nhubot sendgrid blocks # First 10 blocks of today\n\nhubot sendgrid invalids # First 10 invalid emails of today\n\nhubot sendgrid bounces 20 # First 20 bounces of today\n\nhubot sendgrid unsubscribes YYYY-MM-DD # First 10 unsubscribes on YYYY-MM-DD\n\nhubot sendgrid spam reports YYYY-MM-DD 20 # First 20 spam reports on YYYY-MM-DD\n```\n","maintainers":[{"name":"statianzo","email":"jstaten07+npm@gmail.com"}],"time":{"modified":"2017-11-28T23:02:26.230Z","created":"2014-11-01T16:32:53.327Z","0.1.1":"2014-11-01T16:32:53.327Z","0.2.0":"2014-11-03T04:05:07.218Z"},"homepage":"https://github.com/statianzo/hubot-sendgrid","keywords":["hubot","hubot-scripts"],"repository":{"type":"git","url":"https://github.com/statianzo/hubot-sendgrid.git"},"author":{"name":"Jason Staten","email":"jstaten07@gmail.com"},"bugs":{"url":"https://github.com/statianzo/hubot-sendgrid/issues"},"license":"MIT","readmeFilename":"README.md","users":{"ecelis":true}}
