{"_id":"hubot-chatops","_rev":"2-922bc8b8f993709b77c1aafcc5665aa9","name":"hubot-chatops","description":"Hubot plugin for devops","dist-tags":{"latest":"0.0.1"},"versions":{"0.0.1":{"name":"hubot-chatops","version":"0.0.1","description":"Hubot plugin for devops","main":"index.coffee","author":{"name":"Emil Soman"},"license":"MIT","dependencies":{"hubot":"2.x"},"devDependencies":{"coffee-script":"1.x"},"repository":{"type":"git","url":"git+https://github.com/code-mancers/hubot-chatops.git"},"gitHead":"e666fe4c0c353dd688b6ac3c1ab15cfe4f9fb1b6","bugs":{"url":"https://github.com/code-mancers/hubot-chatops/issues"},"homepage":"https://github.com/code-mancers/hubot-chatops#readme","_id":"hubot-chatops@0.0.1","scripts":{},"_shasum":"270f93bddec7bec7986fc00e115d602fe3ced03c","_from":".","_npmVersion":"2.11.3","_nodeVersion":"0.12.7","_npmUser":{"name":"emilsoman","email":"emil.soman@gmail.com"},"maintainers":[{"name":"emilsoman","email":"emil.soman@gmail.com"}],"dist":{"shasum":"270f93bddec7bec7986fc00e115d602fe3ced03c","tarball":"http://registry.npmjs.org/hubot-chatops/-/hubot-chatops-0.0.1.tgz"}}},"readme":"hubot-chatops\n=============\n\nA hubot plugin for devops.\n\nCurrently it integrates with [chatops_deployer](https://github.com/code-mancers/chatops_deployer)\nto deploy and destroy disposable environments.\n\n### Configuration\n\n    DEPLOYER_URL - URL of chatops_deployer\n    HUBOT_URL - URL of hubot itself\n\n### Commands\n\n    @bot deploy feature-branch of github_org/reponame # Deploys\n    @bot destroy feature-branch of github/org/reponame # Destroys deployment\n\n### License\nMIT\n","maintainers":[{"name":"emilsoman","email":"emil.soman@gmail.com"},{"name":"goromlagche","email":"mrinmoy.das91@gmail.com"},{"name":"iffyuva","email":"yuva@codemancers.com"},{"name":"kgrz","email":"kashyap.kmbc@gmail.com"}],"time":{"modified":"2015-10-20T16:38:13.477Z","created":"2015-10-20T16:30:09.820Z","0.0.1":"2015-10-20T16:30:09.820Z"},"homepage":"https://github.com/code-mancers/hubot-chatops#readme","repository":{"type":"git","url":"git+https://github.com/code-mancers/hubot-chatops.git"},"author":{"name":"Emil Soman"},"bugs":{"url":"https://github.com/code-mancers/hubot-chatops/issues"},"license":"MIT","readmeFilename":"README.md"}
