{"_id":"hubot-timezone-converter","_rev":"5-ca526b9431af605ba58b0e833d0a0050","name":"hubot-timezone-converter","description":"Enable hubot to convert times in user time zones during discussion.","dist-tags":{"latest":"3.2.0"},"versions":{"1.0.0":{"name":"hubot-timezone-converter","description":"Enable hubot to convert times in user time zones during discussion.","version":"1.0.0","author":{"name":"Nikolaos Anastopoulos","email":"ebababi@ebababi.net"},"license":"MIT","keywords":["hubot","hubot-scripts"],"repository":{"type":"git","url":"git://github.com/ebababi/hubot-timezone-converter.git"},"bugs":{"url":"https://github.com/ebababi/hubot-timezone-converter/issues"},"dependencies":{"chrono-node":"^1.x","moment-timezone":"^0.x"},"peerDependencies":{"hubot":"2.x","hubot-slack":"3.x"},"devDependencies":{"chai":"^2.1.1","coffee-script":"1.6.3","coffeelint":"^1.14.2","grunt":"^0.4.5","grunt-cli":"^0.1.13","grunt-contrib-watch":"~0.6.1","grunt-mocha-test":"~0.12.7","grunt-release":"~0.11.0","hubot":"2.x","hubot-mock-adapter":"^1.0.0","hubot-slack":"3.x","matchdep":"~0.3.0","mocha":"^2.1.0","node-fixtures":"0.0.1","sinon":"^1.13.0","sinon-chai":"^2.7.0"},"main":"index.coffee","scripts":{"pretest":"coffeelint src test","test":"grunt test"},"coffeelintConfig":{"max_line_length":{"value":120}},"gitHead":"1aeb7bb0c36b19ba50165b7b2de0da7d5e5685e9","homepage":"https://github.com/ebababi/hubot-timezone-converter#readme","_id":"hubot-timezone-converter@1.0.0","_shasum":"5df3989378184b368030c9d1f0ef882633e3b19f","_from":".","_npmVersion":"2.14.18","_nodeVersion":"4.3.0","_npmUser":{"name":"ebababi","email":"ebababi@ebababi.net"},"dist":{"shasum":"5df3989378184b368030c9d1f0ef882633e3b19f","tarball":"http://registry.npmjs.org/hubot-timezone-converter/-/hubot-timezone-converter-1.0.0.tgz"},"maintainers":[{"name":"ebababi","email":"ebababi@ebababi.net"}],"_npmOperationalInternal":{"host":"packages-6-west.internal.npmjs.com","tmp":"tmp/hubot-timezone-converter-1.0.0.tgz_1456358117137_0.12778921704739332"},"directories":{}},"2.0.0":{"name":"hubot-timezone-converter","description":"Enable hubot to convert times in user time zones during discussion.","version":"2.0.0","author":{"name":"Nikolaos Anastopoulos","email":"ebababi@ebababi.net"},"license":"MIT","keywords":["hubot","hubot-scripts"],"repository":{"type":"git","url":"git://github.com/ebababi/hubot-timezone-converter.git"},"bugs":{"url":"https://github.com/ebababi/hubot-timezone-converter/issues"},"dependencies":{"chrono-node":"^1.x","moment-timezone":"^0.x"},"peerDependencies":{"hubot":"2.x","hubot-slack":"3.x"},"devDependencies":{"chai":"^2.1.1","coffee-script":"1.6.3","coffeelint":"^1.14.2","grunt":"^0.4.5","grunt-cli":"^0.1.13","grunt-contrib-watch":"~0.6.1","grunt-mocha-test":"~0.12.7","grunt-release":"~0.11.0","hubot":"2.x","hubot-mock-adapter":"^1.0.0","hubot-slack":"3.x","matchdep":"~0.3.0","mocha":"^2.1.0","node-fixtures":"0.0.1","sinon":"^1.13.0","sinon-chai":"^2.7.0"},"main":"index.coffee","scripts":{"pretest":"coffeelint src test","test":"grunt test"},"coffeelintConfig":{"max_line_length":{"value":120}},"gitHead":"ff2a67c6b4dfc35226d3c21f165f757a1806dfbc","homepage":"https://github.com/ebababi/hubot-timezone-converter#readme","_id":"hubot-timezone-converter@2.0.0","_shasum":"211c140466917a7847bfc8e37e020828b116997c","_from":".","_npmVersion":"2.14.18","_nodeVersion":"4.3.0","_npmUser":{"name":"ebababi","email":"ebababi@ebababi.net"},"dist":{"shasum":"211c140466917a7847bfc8e37e020828b116997c","tarball":"http://registry.npmjs.org/hubot-timezone-converter/-/hubot-timezone-converter-2.0.0.tgz"},"maintainers":[{"name":"ebababi","email":"ebababi@ebababi.net"}],"_npmOperationalInternal":{"host":"packages-12-west.internal.npmjs.com","tmp":"tmp/hubot-timezone-converter-2.0.0.tgz_1457569021585_0.3212055277545005"},"directories":{}},"2.0.1":{"name":"hubot-timezone-converter","description":"Enable hubot to convert times in user time zones during discussion.","version":"2.0.1","author":{"name":"Nikolaos Anastopoulos","email":"ebababi@ebababi.net"},"license":"MIT","keywords":["hubot","hubot-scripts"],"repository":{"type":"git","url":"git://github.com/ebababi/hubot-timezone-converter.git"},"bugs":{"url":"https://github.com/ebababi/hubot-timezone-converter/issues"},"dependencies":{"chrono-node":"^1.x","moment-timezone":"^0.x"},"peerDependencies":{"hubot":"2.x","hubot-slack":"3.x"},"devDependencies":{"chai":"^2.1.1","coffee-script":"1.6.3","coffeelint":"^1.14.2","grunt":"^0.4.5","grunt-cli":"^0.1.13","grunt-contrib-watch":"~0.6.1","grunt-mocha-test":"~0.12.7","grunt-release":"~0.11.0","hubot":"2.x","hubot-mock-adapter":"^1.0.0","hubot-slack":"3.x","matchdep":"~0.3.0","mocha":"^2.1.0","node-fixtures":"0.0.1","sinon":"^1.13.0","sinon-chai":"^2.7.0"},"main":"index.coffee","scripts":{"pretest":"coffeelint src test","test":"grunt test"},"coffeelintConfig":{"max_line_length":{"value":120}},"gitHead":"86f42be4db1f9aff141f811a369a077bdad70b43","homepage":"https://github.com/ebababi/hubot-timezone-converter#readme","_id":"hubot-timezone-converter@2.0.1","_shasum":"c30ebcb3206bfde92570612be5a58aed95043b42","_from":".","_npmVersion":"2.14.18","_nodeVersion":"4.3.0","_npmUser":{"name":"ebababi","email":"ebababi@ebababi.net"},"dist":{"shasum":"c30ebcb3206bfde92570612be5a58aed95043b42","tarball":"http://registry.npmjs.org/hubot-timezone-converter/-/hubot-timezone-converter-2.0.1.tgz"},"maintainers":[{"name":"ebababi","email":"ebababi@ebababi.net"}],"_npmOperationalInternal":{"host":"packages-12-west.internal.npmjs.com","tmp":"tmp/hubot-timezone-converter-2.0.1.tgz_1457570269209_0.010289718862622976"},"directories":{}},"3.0.0":{"name":"hubot-timezone-converter","description":"Enable hubot to convert times in user time zones during discussion.","version":"3.0.0","author":{"name":"Nikolaos Anastopoulos","email":"ebababi@ebababi.net"},"license":"MIT","keywords":["hubot","hubot-scripts"],"repository":{"type":"git","url":"git://github.com/ebababi/hubot-timezone-converter.git"},"bugs":{"url":"https://github.com/ebababi/hubot-timezone-converter/issues"},"dependencies":{"chrono-node":"^1.x","moment-timezone":"^0.x"},"peerDependencies":{"hubot":"2.x","hubot-slack":"4.x"},"devDependencies":{"chai":"~2.1.0","coffee-script":"~1.6.3","coffeelint":"^1.16.0","grunt":"^0.4.5","grunt-cli":"^0.1.13","grunt-contrib-watch":"^0.6.1","grunt-mocha-test":"^0.12.7","grunt-release":"^0.13.1","hubot":"2.x","hubot-mock-adapter":"^1.0.0","hubot-slack":"4.x","matchdep":"^2.0.0","mocha":"^2.1.0","node-fixtures":"0.0.1","sinon":"~1.17.0","sinon-chai":"^2.8.0"},"main":"index.coffee","scripts":{"pretest":"coffeelint src test","test":"grunt test"},"coffeelintConfig":{"max_line_length":{"value":120}},"gitHead":"800070356f4b8502c98574c18470931de5420492","homepage":"https://github.com/ebababi/hubot-timezone-converter#readme","_id":"hubot-timezone-converter@3.0.0","_shasum":"7ff30c7364e5d7a3cee586f7eb56ba85552e5840","_from":".","_npmVersion":"3.10.10","_nodeVersion":"6.12.3","_npmUser":{"name":"ebababi","email":"ebababi@ebababi.net"},"dist":{"shasum":"7ff30c7364e5d7a3cee586f7eb56ba85552e5840","tarball":"https://registry.npmjs.org/hubot-timezone-converter/-/hubot-timezone-converter-3.0.0.tgz"},"maintainers":[{"name":"ebababi","email":"ebababi@ebababi.net"}],"_npmOperationalInternal":{"host":"s3://npm-registry-packages","tmp":"tmp/hubot-timezone-converter-3.0.0.tgz_1515355973316_0.3676618367899209"},"directories":{}},"3.1.0":{"name":"hubot-timezone-converter","description":"Enable hubot to convert times in user time zones during discussion.","version":"3.1.0","author":{"name":"Nikolaos Anastopoulos","email":"ebababi@ebababi.net"},"license":"MIT","keywords":["hubot","hubot-scripts"],"repository":{"type":"git","url":"git://github.com/ebababi/hubot-timezone-converter.git"},"bugs":{"url":"https://github.com/ebababi/hubot-timezone-converter/issues"},"dependencies":{"chrono-node":"^1.x","moment-timezone":"^0.x"},"peerDependencies":{"hubot":"2.x","hubot-slack":"4.x"},"devDependencies":{"chai":"~2.1.0","coffee-script":"~1.6.3","coffeelint":"^1.16.0","grunt":"^0.4.5","grunt-cli":"^0.1.13","grunt-contrib-watch":"^0.6.1","grunt-mocha-test":"^0.12.7","grunt-release":"^0.13.1","hubot":"2.x","hubot-mock-adapter":"^1.0.0","hubot-slack":"4.x","matchdep":"^2.0.0","mocha":"^2.1.0","node-fixtures":"0.0.1","sinon":"~1.17.0","sinon-chai":"^2.8.0"},"main":"index.coffee","scripts":{"pretest":"coffeelint src test","test":"grunt test"},"coffeelintConfig":{"max_line_length":{"value":120}},"gitHead":"d55f037e83e4ac87ada7872cd4cc3679133be7b9","homepage":"https://github.com/ebababi/hubot-timezone-converter#readme","_id":"hubot-timezone-converter@3.1.0","_shasum":"af1bcc7ae379350fc068aedfa8aca8dc96355d1a","_from":".","_npmVersion":"3.10.10","_nodeVersion":"6.13.1","_npmUser":{"name":"ebababi","email":"ebababi@ebababi.net"},"dist":{"shasum":"af1bcc7ae379350fc068aedfa8aca8dc96355d1a","tarball":"http://registry.npmjs.org/hubot-timezone-converter/-/hubot-timezone-converter-3.1.0.tgz","fileCount":14,"unpackedSize":11513},"maintainers":[{"name":"ebababi","email":"ebababi@ebababi.net"}],"directories":{},"_npmOperationalInternal":{"host":"s3://npm-registry-packages","tmp":"tmp/hubot-timezone-converter_3.1.0_1520723916078_0.639403929123685"},"_hasShrinkwrap":false},"3.2.0":{"name":"hubot-timezone-converter","description":"Enable hubot to convert times in user time zones during discussion.","version":"3.2.0","author":{"name":"Nikolaos Anastopoulos","email":"ebababi@ebababi.net"},"license":"MIT","keywords":["hubot","hubot-scripts"],"repository":{"type":"git","url":"git://github.com/ebababi/hubot-timezone-converter.git"},"bugs":{"url":"https://github.com/ebababi/hubot-timezone-converter/issues"},"dependencies":{"chrono-node":"^1.x","moment-timezone":"^0.x"},"peerDependencies":{"hubot":"2.x","hubot-slack":"^4.5"},"devDependencies":{"bluebird":"^3.5.1","chai":"~2.1.0","coffee-script":"~1.6.3","coffeelint":"^1.16.0","grunt":"^0.4.5","grunt-cli":"^0.1.13","grunt-contrib-watch":"^0.6.1","grunt-mocha-test":"^0.12.7","grunt-release":"^0.13.1","hubot":"2.x","hubot-slack":"^4.5","matchdep":"^2.0.0","mocha":"^2.1.0","mockery":"^1.4.0","node-fixtures":"0.0.1","sinon":"~1.17.0","sinon-chai":"^2.8.0"},"main":"index.coffee","scripts":{"pretest":"coffeelint src test","test":"grunt test"},"coffeelintConfig":{"max_line_length":{"value":120}},"gitHead":"9b51afa1cdd31091dfcfe49ae226a77425a1d535","homepage":"https://github.com/ebababi/hubot-timezone-converter#readme","_id":"hubot-timezone-converter@3.2.0","_npmVersion":"6.1.0","_nodeVersion":"8.11.3","_npmUser":{"name":"ebababi","email":"ebababi@ebababi.net"},"dist":{"integrity":"sha512-4aYPon8qlz4qpTOLtHtmsG+ecrvfWv7v401oDDHTWOjJ7CJ+czKes0sDX8sems28rEJHW50QNcgycySdZ86UsA==","shasum":"2ccdbab103c0c5978755d09ba3af7cbfd86859d2","tarball":"https://registry.npmjs.org/hubot-timezone-converter/-/hubot-timezone-converter-3.2.0.tgz","fileCount":14,"unpackedSize":13535,"npm-signature":"-----BEGIN PGP SIGNATURE-----\r\nVersion: OpenPGP.js v3.0.4\r\nComment: https://openpgpjs.org\r\n\r\nwsFcBAEBCAAQBQJbZi7xCRA9TVsSAnZWagAAmKUP/0nYoeU+U7CqSl2CFUOg\nPnkY8y10n3qR2Ud2RoImnmUWg9XGexPYY0wYv4DkuLyfeom7EEJqZ3yn68/x\nVrPaEWq6r4FFQmQc96R4gj7RCsqwAnHe2cv1b82tRVIyZztVyBUjXAflsmnA\nryF2pzLq4MlZBXeN4EehHiVMcDJnML5lUk3LYe1XWszeWs1Ilif97bqJUydX\nfztnzneG2hkjmazRyJ3lURXnp+jq0rgt5mc1EVVMqEXrZ11oAXJfJSP8+NNE\nVveMrQhmz4ORWthPIFvZMmQ1uVn/ryYtdn+OmQu+WqVu3tPX5LxImuE714UX\nULZVM8ZxZVKs2rCgoR0JmA8y+E7tXr0SRcetuP1CXLUWKUnfXwu4rbE/uQPt\nFNZyyYiBYIh2j15D5cviUiLgf7ja4GryWDZr6ndlC0YmHsQgZq5MI9x+TNU1\ndIksauMyNrrSbOHgoHeY5o3O42bgTOWCob0m/DaPWjHf/y5I3unmv3bH9pun\nHgfTgDsLbsFxYRhmI3Dms0s8TLWEcNIfLBXCgnXhyrzfIADnQexB0womfexX\nnEIm8Z5MBsHu0jpH+Scx8mB0/P+dr3dX4EmAEf9teTK3A+ii3UG2mSGIO8sG\nmHCTYx90K81DMUoIMIr2RcCnHF6kaFWJHtIKcM0PsCkubSBs2jMp1PQt0lh7\noT1v\r\n=4oee\r\n-----END PGP SIGNATURE-----\r\n"},"maintainers":[{"name":"ebababi","email":"ebababi@ebababi.net"}],"directories":{},"_npmOperationalInternal":{"host":"s3://npm-registry-packages","tmp":"tmp/hubot-timezone-converter_3.2.0_1533423345512_0.5816896088735921"},"_hasShrinkwrap":false}},"readme":"# hubot-timezone-converter\n\nEnable hubot to convert times in user time zones during discussion.\n\nSee [`src/timezone-converter.coffee`](src/timezone-converter.coffee) for full documentation.\n\n## Installation\n\nIn hubot project repo, run:\n\n`npm install hubot-timezone-converter --save`\n\nThen add **hubot-timezone-converter** to your `external-scripts.json`:\n\n```json\n[\n  \"hubot-timezone-converter\"\n]\n```\n\n## Sample Interaction\n\n```\nuser1>> team meeting at 4am\nhubot>> 21:00 (Eastern Standard Time)\n        03:00 (Central European Time)\n        04:00 (Eastern European Time)\n```\n","maintainers":[{"name":"ebababi","email":"ebababi@ebababi.net"}],"time":{"modified":"2018-08-04T22:55:48.325Z","created":"2016-02-24T23:55:19.683Z","1.0.0":"2016-02-24T23:55:19.683Z","2.0.0":"2016-03-10T00:17:03.767Z","2.0.1":"2016-03-10T00:37:51.512Z","3.0.0":"2018-01-07T20:12:53.402Z","3.1.0":"2018-03-10T23:18:36.131Z","3.2.0":"2018-08-04T22:55:45.603Z"},"homepage":"https://github.com/ebababi/hubot-timezone-converter#readme","keywords":["hubot","hubot-scripts"],"repository":{"type":"git","url":"git://github.com/ebababi/hubot-timezone-converter.git"},"author":{"name":"Nikolaos Anastopoulos","email":"ebababi@ebababi.net"},"bugs":{"url":"https://github.com/ebababi/hubot-timezone-converter/issues"},"license":"MIT","readmeFilename":"README.md","users":{"ebababi":true}}
