{"_id":"hubot-tube-status","_rev":"2-d9d4dc8350e2917fe47d689e1ef8e0e3","name":"hubot-tube-status","description":"Get the tube status from transport for london (TFL)","dist-tags":{"latest":"0.1.2"},"versions":{"0.0.0":{"name":"hubot-tube-status","description":"Get the tube status from transport for london (TFL)","version":"0.0.0","author":{"name":"Wilfred Hughes","email":"me@wilfred.me.uk"},"license":"MIT","keywords":["hubot","hubot-scripts"],"repository":{"type":"git","url":"git://github.com/hubot-scripts/hubot-tube-status.git"},"bugs":{"url":"https://github.com/hubot-scripts/hubot-tube-status/issues"},"dependencies":{"coffee-script":"~1.6","underscore":"^1.8.2","xml2json":"^0.6.1"},"devDependencies":{"mocha":"*","chai":"*","sinon-chai":"*","sinon":"*","grunt-mocha-test":"~0.7.0","grunt-release":"~0.6.0","matchdep":"~0.1.2","grunt-contrib-watch":"~0.5.3"},"main":"index.coffee","scripts":{"test":"grunt test"},"gitHead":"2f17cdc5e63363b75f48968a9df2ed4853884075","homepage":"https://github.com/hubot-scripts/hubot-tube-status","_id":"hubot-tube-status@0.0.0","_shasum":"ccc0e3618e3193f817cd4c16e58a3e749e229250","_from":".","_npmVersion":"2.6.0","_nodeVersion":"0.12.0","_npmUser":{"name":"wilfredh","email":"me@wilfred.me.uk"},"maintainers":[{"name":"wilfredh","email":"me@wilfred.me.uk"}],"dist":{"shasum":"ccc0e3618e3193f817cd4c16e58a3e749e229250","tarball":"http://registry.npmjs.org/hubot-tube-status/-/hubot-tube-status-0.0.0.tgz"}},"0.1.1":{"name":"hubot-tube-status","description":"Get the tube status from transport for london (TFL)","version":"0.1.1","author":{"name":"Wilfred Hughes","email":"me@wilfred.me.uk"},"license":"MIT","keywords":["hubot","hubot-scripts"],"repository":{"type":"git","url":"git://github.com/hubot-scripts/hubot-tube-status.git"},"bugs":{"url":"https://github.com/hubot-scripts/hubot-tube-status/issues"},"dependencies":{"coffee-script":"~1.6","underscore":"^1.8.2","xml2json":"^0.6.1"},"devDependencies":{"mocha":"*","chai":"*","sinon-chai":"*","sinon":"*","grunt-mocha-test":"~0.7.0","grunt-release":"~0.6.0","matchdep":"~0.1.2","grunt-contrib-watch":"~0.5.3"},"main":"index.coffee","scripts":{"test":"grunt test"},"gitHead":"a8c59f16a520c55c36080dc184914f511b35e6c6","homepage":"https://github.com/hubot-scripts/hubot-tube-status","_id":"hubot-tube-status@0.1.1","_shasum":"422f0144ad2b71c7ef2843c197d305161d9ea484","_from":".","_npmVersion":"2.6.0","_nodeVersion":"0.12.0","_npmUser":{"name":"wilfredh","email":"me@wilfred.me.uk"},"maintainers":[{"name":"wilfredh","email":"me@wilfred.me.uk"}],"dist":{"shasum":"422f0144ad2b71c7ef2843c197d305161d9ea484","tarball":"http://registry.npmjs.org/hubot-tube-status/-/hubot-tube-status-0.1.1.tgz"}},"0.1.2":{"name":"hubot-tube-status","description":"Get the tube status from transport for london (TFL)","version":"0.1.2","author":{"name":"Wilfred Hughes","email":"me@wilfred.me.uk"},"license":"MIT","keywords":["hubot","hubot-scripts"],"repository":{"type":"git","url":"git://github.com/hubot-scripts/hubot-tube-status.git"},"bugs":{"url":"https://github.com/hubot-scripts/hubot-tube-status/issues"},"dependencies":{"coffee-script":"~1.6","underscore":"^1.8.2","xml2json":"^0.6.1"},"devDependencies":{"mocha":"*","chai":"*","sinon-chai":"*","sinon":"*","grunt-mocha-test":"~0.7.0","grunt-release":"~0.6.0","matchdep":"~0.1.2","grunt-contrib-watch":"~0.5.3"},"main":"index.coffee","scripts":{"test":"grunt test"},"gitHead":"682558b2b77d2eb5f61d033ee139d528c6962515","homepage":"https://github.com/hubot-scripts/hubot-tube-status","_id":"hubot-tube-status@0.1.2","_shasum":"c2185b7979e4671fbd5018aafc1976caa0f2b5da","_from":".","_npmVersion":"2.6.0","_nodeVersion":"0.12.0","_npmUser":{"name":"wilfredh","email":"me@wilfred.me.uk"},"maintainers":[{"name":"wilfredh","email":"me@wilfred.me.uk"}],"dist":{"shasum":"c2185b7979e4671fbd5018aafc1976caa0f2b5da","tarball":"http://registry.npmjs.org/hubot-tube-status/-/hubot-tube-status-0.1.2.tgz"}}},"readme":"# hubot-tube-status\n\n[![Build Status](https://travis-ci.org/Wilfred/hubot-tube-status.svg?branch=master)](https://travis-ci.org/Wilfred/hubot-tube-status)\n\nGet the tube status from transport for london (TFL) using the TfL\nOpen Data API.\n\nSee [`src/tube-status.coffee`](src/tube-status.coffee) for full documentation.\n\n## Installation\n\nIn hubot project repo, run:\n\n`npm install hubot-tube-status --save`\n\nThen add **hubot-tube-status** to your `external-scripts.json`:\n\n```json\n[\"hubot-tube-status\"]\n```\n\n## Sample Interaction\n\n```\nuser> hubot tube status\nHubot> District: Part closure from Aldgate East to Upminster.\nHammersmith and City: Part closure from Liverpool Street to Barking.\nOverground: Part closure from Clapham Junction to Kensington (Olympia), Gospel Oak to Stratford, Highbury & Islington to Shadwell and Sydenham to Crystal Palace.\nWaterloo and City: Train service resumes at 0615 on Monday.\n```\n\n## Changelog\n\n### v0.1.2\n\nFixed an issue where Hubot didn't respond if all lines were running as\nnormal.\n\n### v0.1.1\n\nInitial release.\n","maintainers":[{"name":"wilfredh","email":"me@wilfred.me.uk"}],"time":{"modified":"2015-02-24T20:49:20.797Z","created":"2015-02-22T16:10:17.658Z","0.0.0":"2015-02-22T16:10:17.658Z","0.1.1":"2015-02-22T16:17:33.916Z","0.1.2":"2015-02-24T20:49:20.797Z"},"homepage":"https://github.com/hubot-scripts/hubot-tube-status","keywords":["hubot","hubot-scripts"],"repository":{"type":"git","url":"git://github.com/hubot-scripts/hubot-tube-status.git"},"author":{"name":"Wilfred Hughes","email":"me@wilfred.me.uk"},"bugs":{"url":"https://github.com/hubot-scripts/hubot-tube-status/issues"},"license":"MIT","readmeFilename":"README.md"}
