{"_id":"hubot-relay","_rev":"2-afc306ed198c9226161d93ba64ae25ce","name":"hubot-relay","description":"Relay message to another chatbox via http","dist-tags":{"latest":"0.1.4"},"versions":{"0.1.0":{"name":"hubot-relay","version":"0.1.0","description":"Relay message to another chatbox via http","main":"index.coffee","scripts":{"test":"echo \"Error: no test specified\" && exit 1"},"repository":{"type":"git","url":"git+https://github.com/yuyuvn/hubot-relay.git"},"keywords":["hubot","hubot-scripts","relay"],"author":{"name":"Clicia Scarlet","email":"yuyuvn@icloud.com"},"license":"MIT","bugs":{"url":"https://github.com/yuyuvn/hubot-relay/issues"},"homepage":"https://github.com/yuyuvn/hubot-relay","dependencies":{"coffee-script":"^1.6.0"},"gitHead":"a13655a352d44ee2c6d5400ba143649529cbd8a5","_id":"hubot-relay@0.1.0","_shasum":"8a55c32187c637562808e5999e92862fd07f2bc3","_from":".","_npmVersion":"3.8.3","_nodeVersion":"0.10.25","_npmUser":{"name":"yuyuvn","email":"yuyuvn@mac.com"},"dist":{"shasum":"8a55c32187c637562808e5999e92862fd07f2bc3","tarball":"http://registry.npmjs.org/hubot-relay/-/hubot-relay-0.1.0.tgz"},"maintainers":[{"name":"yuyuvn","email":"yuyuvn@mac.com"}],"_npmOperationalInternal":{"host":"packages-12-west.internal.npmjs.com","tmp":"tmp/hubot-relay-0.1.0.tgz_1459137913213_0.2998037454672158"}},"0.1.1":{"name":"hubot-relay","version":"0.1.1","description":"Relay message to another chatbox via http","main":"index.coffee","scripts":{"test":"echo \"Error: no test specified\" && exit 1"},"repository":{"type":"git","url":"git+https://github.com/yuyuvn/hubot-relay.git"},"keywords":["hubot","hubot-scripts","relay"],"author":{"name":"Clicia Scarlet","email":"yuyuvn@icloud.com"},"license":"MIT","bugs":{"url":"https://github.com/yuyuvn/hubot-relay/issues"},"homepage":"https://github.com/yuyuvn/hubot-relay","dependencies":{"coffee-script":"^1.6.0"},"gitHead":"b4852c4e5cabff5a8264b52f091bb0f42fb123ab","_id":"hubot-relay@0.1.1","_shasum":"189be32c1fe522c1bf350f57477b88d760547312","_from":".","_npmVersion":"3.8.3","_nodeVersion":"0.10.25","_npmUser":{"name":"yuyuvn","email":"yuyuvn@mac.com"},"dist":{"shasum":"189be32c1fe522c1bf350f57477b88d760547312","tarball":"http://registry.npmjs.org/hubot-relay/-/hubot-relay-0.1.1.tgz"},"maintainers":[{"name":"yuyuvn","email":"yuyuvn@mac.com"}],"_npmOperationalInternal":{"host":"packages-12-west.internal.npmjs.com","tmp":"tmp/hubot-relay-0.1.1.tgz_1459139090330_0.45675046811811626"}},"0.1.2":{"name":"hubot-relay","version":"0.1.2","description":"Relay message to another chatbox via http","main":"index.coffee","scripts":{"test":"echo \"Error: no test specified\" && exit 1"},"repository":{"type":"git","url":"git+https://github.com/yuyuvn/hubot-relay.git"},"keywords":["hubot","hubot-scripts","relay"],"author":{"name":"Clicia Scarlet","email":"yuyuvn@icloud.com"},"license":"MIT","bugs":{"url":"https://github.com/yuyuvn/hubot-relay/issues"},"homepage":"https://github.com/yuyuvn/hubot-relay","dependencies":{"coffee-script":"^1.6.0"},"gitHead":"6956c524cfecf6bca8d8576c0adc32efc8c780fb","_id":"hubot-relay@0.1.2","_shasum":"1faad0ad536f8b530854b3efdc46c44a7ceae8a9","_from":".","_npmVersion":"3.8.3","_nodeVersion":"0.10.25","_npmUser":{"name":"yuyuvn","email":"yuyuvn@mac.com"},"dist":{"shasum":"1faad0ad536f8b530854b3efdc46c44a7ceae8a9","tarball":"http://registry.npmjs.org/hubot-relay/-/hubot-relay-0.1.2.tgz"},"maintainers":[{"name":"yuyuvn","email":"yuyuvn@mac.com"}],"_npmOperationalInternal":{"host":"packages-12-west.internal.npmjs.com","tmp":"tmp/hubot-relay-0.1.2.tgz_1459139585377_0.7860069740563631"}},"0.1.3":{"name":"hubot-relay","version":"0.1.3","description":"Relay message to another chatbox via http","main":"index.coffee","scripts":{"test":"echo \"Error: no test specified\" && exit 1"},"repository":{"type":"git","url":"git+https://github.com/yuyuvn/hubot-relay.git"},"keywords":["hubot","hubot-scripts","relay"],"author":{"name":"Clicia Scarlet","email":"yuyuvn@icloud.com"},"license":"MIT","bugs":{"url":"https://github.com/yuyuvn/hubot-relay/issues"},"homepage":"https://github.com/yuyuvn/hubot-relay","dependencies":{"coffee-script":"^1.6.0"},"gitHead":"380587e65d5502d67d45db6fe75336665fdde16c","_id":"hubot-relay@0.1.3","_shasum":"2b7cef9c65eba836cb2d41da5d97361ac432c270","_from":".","_npmVersion":"3.7.3","_nodeVersion":"5.8.0","_npmUser":{"name":"yuyuvn","email":"yuyuvn@mac.com"},"dist":{"shasum":"2b7cef9c65eba836cb2d41da5d97361ac432c270","tarball":"http://registry.npmjs.org/hubot-relay/-/hubot-relay-0.1.3.tgz"},"maintainers":[{"name":"yuyuvn","email":"yuyuvn@mac.com"}],"_npmOperationalInternal":{"host":"packages-12-west.internal.npmjs.com","tmp":"tmp/hubot-relay-0.1.3.tgz_1459232331028_0.7828823192976415"}},"0.1.4":{"name":"hubot-relay","version":"0.1.4","description":"Relay message to another chatbox via http","main":"index.coffee","scripts":{"test":"echo \"Error: no test specified\" && exit 1"},"repository":{"type":"git","url":"git+https://github.com/yuyuvn/hubot-relay.git"},"keywords":["hubot","hubot-scripts","relay"],"author":{"name":"Clicia Scarlet","email":"yuyuvn@icloud.com"},"license":"MIT","bugs":{"url":"https://github.com/yuyuvn/hubot-relay/issues"},"homepage":"https://github.com/yuyuvn/hubot-relay","devDependencies":{"coffee-script":"^1.6.0"},"gitHead":"7dcc9fc78eb7ea7bd99b665b4744b2473dd5bd88","_id":"hubot-relay@0.1.4","_shasum":"66ebd0fca015b46f5bd8c369ec27fbd5c4ad4394","_from":".","_npmVersion":"3.8.6","_nodeVersion":"4.4.2","_npmUser":{"name":"yuyuvn","email":"yuyuvn@mac.com"},"dist":{"shasum":"66ebd0fca015b46f5bd8c369ec27fbd5c4ad4394","tarball":"http://registry.npmjs.org/hubot-relay/-/hubot-relay-0.1.4.tgz"},"maintainers":[{"name":"yuyuvn","email":"yuyuvn@mac.com"}],"_npmOperationalInternal":{"host":"packages-16-east.internal.npmjs.com","tmp":"tmp/hubot-relay-0.1.4.tgz_1461915347511_0.8127283044159412"}}},"readme":"hubot-relay\r\n============\r\n\r\nRelay message to another chatbox via http\r\n\r\n\r\n## Installation\r\n\r\nAdd **hubot-relay** to your `package.json` file:\r\n\r\n```json\r\n\"dependencies\": {\r\n  \"hubot-relay\": \"*\"\r\n}\r\n```\r\n\r\nOR run `npm install --save hubot-relay`\r\n\r\nAdd **hubot-relay** to your `external-scripts.json`:\r\n\r\n```json\r\n[\"hubot-relay\"]\r\n```\r\n\r\nRun `npm install`\r\n\r\n\r\n## Configuration\r\n\r\n```\r\nRELAY_EVERYTHING - Relay message that didn't call bot name\r\nRELAY_URL - URL relay to\r\nRELAY_RESPONSE - Bot will respond even when relay successfully\r\nRELAY_ENABLE_COMMAND - Support command\r\nRELAY_ENABLE_RECEIVE - Enable receive relay message\r\n```\r\n\r\n- Uri is `http://<your_receiver_address>/hubot/relay/<room_id>`\r\n","maintainers":[{"name":"yuyuvn","email":"yuyuvn@mac.com"}],"time":{"modified":"2016-04-29T07:35:49.647Z","created":"2016-03-28T04:05:13.639Z","0.1.0":"2016-03-28T04:05:13.639Z","0.1.1":"2016-03-28T04:24:50.762Z","0.1.2":"2016-03-28T04:33:05.814Z","0.1.3":"2016-03-29T06:18:51.478Z","0.1.4":"2016-04-29T07:35:49.647Z"},"homepage":"https://github.com/yuyuvn/hubot-relay","keywords":["hubot","hubot-scripts","relay"],"repository":{"type":"git","url":"git+https://github.com/yuyuvn/hubot-relay.git"},"author":{"name":"Clicia Scarlet","email":"yuyuvn@icloud.com"},"bugs":{"url":"https://github.com/yuyuvn/hubot-relay/issues"},"license":"MIT","readmeFilename":"README.md"}
